simpleppt/SimplePPT.py
simpleppt/__init__.py
simpleppt/load_data.py
simpleppt/logging.py
simpleppt/ppt.py
simpleppt/project_ppt.py
simpleppt/settings.py
simpleppt/utils.py
simpleppt/data/diffusion.csv
simpleppt/data/umap.csv
simpleppt-1.1.4.dist-info/LICENSE
simpleppt-1.1.4.dist-info/METADATA
simpleppt-1.1.4.dist-info/WHEEL
simpleppt-1.1.4.dist-info/top_level.txt
simpleppt-1.1.4.dist-info/RECORD
