Metadata-Version: 2.1
Name: simpleppt
Version: 1.1.4
Summary: Python implementation of SimplePPT algorithm, with GPU acceleration
Home-page: https://github.com/LouisFaure/SimplePPT
Author: Louis Faure
Author-email: 
License: UNKNOWN
Platform: UNKNOWN
Requires-Dist: numba >=0.51.2
Requires-Dist: tqdm >=4.45.0
Requires-Dist: scipy >=1.4.1
Requires-Dist: pandas >=1.1.1
Requires-Dist: numpy >=1.18.1
Requires-Dist: matplotlib >=3.2.1
Requires-Dist: python-igraph >=0.8.2
Requires-Dist: scikit-learn
